package_2/__init__.py
package_2/__main__.py
sem_6_package_2-1.0.0.dist-info/METADATA
sem_6_package_2-1.0.0.dist-info/WHEEL
sem_6_package_2-1.0.0.dist-info/top_level.txt
sem_6_package_2-1.0.0.dist-info/RECORD
